fake_session_maker/__init__.py
fake_session_maker/fsm.py
fake_session_maker/py.typed
fake_session_maker-0.3.0.dist-info/METADATA
fake_session_maker-0.3.0.dist-info/WHEEL
fake_session_maker-0.3.0.dist-info/licenses/AUTHORS.rst
fake_session_maker-0.3.0.dist-info/licenses/LICENSE
fake_session_maker-0.3.0.dist-info/RECORD
