Metadata-Version: 2.1
Name: fake_session_maker
Version: 0.3.0
Summary: Create a SQLAlchemy session_maker that won't commit to db for testing purposes.
Project-URL: Bug Tracker, https://lab.frogg.it/dorianturba/fake_session_maker
Project-URL: Homepage, https://lab.frogg.it/dorianturba/fake_session_maker
Author-email: Dorian Turba <contact.5rgbj@8shield.net>
License-File: AUTHORS.rst
License-File: LICENSE
Classifier: Development Status :: 4 - Beta
Classifier: License :: OSI Approved :: MIT License
Classifier: Operating System :: OS Independent
Classifier: Programming Language :: Python :: 3
Classifier: Programming Language :: Python :: 3.7
Classifier: Programming Language :: Python :: 3.8
Classifier: Programming Language :: Python :: 3.9
Classifier: Programming Language :: Python :: 3.10
Classifier: Programming Language :: Python :: 3.11
Classifier: Typing :: Typed
Requires-Python: >=3.7
Requires-Dist: pytest<8,>=7
Requires-Dist: sqlalchemy<3,>=2
Provides-Extra: all
Requires-Dist: fake-session-maker[manage]; extra == 'all'
Requires-Dist: fake-session-maker[quality]; extra == 'all'
Requires-Dist: fake-session-maker[test]; extra == 'all'
Provides-Extra: manage
Requires-Dist: bump-my-version; extra == 'manage'
Provides-Extra: quality
Requires-Dist: black; extra == 'quality'
Requires-Dist: flake8; extra == 'quality'
Requires-Dist: isort; extra == 'quality'
Requires-Dist: mypy; extra == 'quality'
Requires-Dist: pre-commit; extra == 'quality'
Requires-Dist: ruff; extra == 'quality'
Requires-Dist: toml-sort; extra == 'quality'
Provides-Extra: requirements
Requires-Dist: pip-tools; extra == 'requirements'
Provides-Extra: test
Requires-Dist: asyncpg<1.0; extra == 'test'
Requires-Dist: coverage; extra == 'test'
Requires-Dist: psycopg2<3.0; extra == 'test'
Requires-Dist: pytest-asyncio; extra == 'test'
